agentune/simulate/__init__.py
agentune/simulate/channels/__init__.py
agentune/simulate/channels/base.py
agentune/simulate/intent_extraction/__init__.py
agentune/simulate/intent_extraction/base.py
agentune/simulate/intent_extraction/prompts.py
agentune/simulate/intent_extraction/zeroshot.py
agentune/simulate/models/__init__.py
agentune/simulate/models/analysis.py
agentune/simulate/models/conversation.py
agentune/simulate/models/intent.py
agentune/simulate/models/message.py
agentune/simulate/models/outcome.py
agentune/simulate/models/results.py
agentune/simulate/models/roles.py
agentune/simulate/models/scenario.py
agentune/simulate/outcome_detection/__init__.py
agentune/simulate/outcome_detection/base.py
agentune/simulate/outcome_detection/rag/prompt.py
agentune/simulate/outcome_detection/rag/rag.py
agentune/simulate/outcome_detection/zeroshot.py
agentune/simulate/participants/__init__.py
agentune/simulate/participants/agent/__init__.py
agentune/simulate/participants/agent/base.py
agentune/simulate/participants/agent/config.py
agentune/simulate/participants/agent/rag/__init__.py
agentune/simulate/participants/agent/rag/prompt.py
agentune/simulate/participants/agent/rag/rag.py
agentune/simulate/participants/agent/real/__init__.py
agentune/simulate/participants/agent/real/real.py
agentune/simulate/participants/agent/zero_shot/__init__.py
agentune/simulate/participants/agent/zero_shot/prompts.py
agentune/simulate/participants/agent/zero_shot/zero_shot.py
agentune/simulate/participants/base.py
agentune/simulate/participants/customer/__init__.py
agentune/simulate/participants/customer/base.py
agentune/simulate/participants/customer/rag/__init__.py
agentune/simulate/participants/customer/rag/_customer_response.py
agentune/simulate/participants/customer/rag/first_message_prompt.py
agentune/simulate/participants/customer/rag/prompt.py
agentune/simulate/participants/customer/rag/rag.py
agentune/simulate/participants/customer/zero_shot/__init__.py
agentune_simulate-0.0.4.dist-info/METADATA
agentune_simulate-0.0.4.dist-info/WHEEL
agentune_simulate-0.0.4.dist-info/RECORD
